toptica_lasersdk-3.2.0-py3.10-nspkg.pth
toptica/lasersdk/__init__.py
toptica/lasersdk/client.py
toptica/lasersdk/decop.py
toptica/lasersdk/lasersdk_gen.py
toptica/lasersdk/py.typed
toptica/lasersdk/asyncio/__init__.py
toptica/lasersdk/asyncio/client.py
toptica/lasersdk/asyncio/connection.py
toptica/lasersdk/asyncio/dlcpro/__init__.py
toptica/lasersdk/asyncio/dlcpro/v1_4_0.py
toptica/lasersdk/asyncio/dlcpro/v1_5_1.py
toptica/lasersdk/asyncio/dlcpro/v1_6_1.py
toptica/lasersdk/asyncio/dlcpro/v1_6_3.py
toptica/lasersdk/asyncio/dlcpro/v1_7_0.py
toptica/lasersdk/asyncio/dlcpro/v1_8_1.py
toptica/lasersdk/asyncio/dlcpro/v1_9_0.py
toptica/lasersdk/asyncio/dlcpro/v2_0_1.py
toptica/lasersdk/asyncio/dlcpro/v2_0_3.py
toptica/lasersdk/asyncio/dlcpro/v2_1_0.py
toptica/lasersdk/asyncio/dlcpro/v2_2_0.py
toptica/lasersdk/asyncio/dlcpro/v2_3_0.py
toptica/lasersdk/asyncio/dlcpro/v2_3_2.py
toptica/lasersdk/asyncio/dlcpro/v2_3_4.py
toptica/lasersdk/asyncio/dlcpro/v2_4_0.py
toptica/lasersdk/asyncio/dlcpro/v2_5_2.py
toptica/lasersdk/asyncio/dlcpro/v2_5_3.py
toptica/lasersdk/asyncio/dlcpro/v2_5_4.py
toptica/lasersdk/asyncio/dlcpro/v2_6_0.py
toptica/lasersdk/asyncio/dlcpro/v2_7_2.py
toptica/lasersdk/asyncio/dlcpro/v3_0_1.py
toptica/lasersdk/asyncio/dlcpro/v3_1_0.py
toptica/lasersdk/asyncio/dlcpro/v3_2_0.py
toptica/lasersdk/asyncio/ichrome_cle/__init__.py
toptica/lasersdk/asyncio/ichrome_cle/v1_0_8.py
toptica/lasersdk/asyncio/ichrome_cle/v1_1_3.py
toptica/lasersdk/asyncio/ichrome_cle/v2_2_5.py
toptica/lasersdk/asyncio/ichrome_mle/__init__.py
toptica/lasersdk/asyncio/ichrome_mle/v1_8_1.py
toptica/lasersdk/asyncio/ichrome_mle/v2_2_0.py
toptica/lasersdk/asyncio/ichrome_mle/v2_3_1.py
toptica/lasersdk/dlcpro/__init__.py
toptica/lasersdk/dlcpro/v1_4_0.py
toptica/lasersdk/dlcpro/v1_5_1.py
toptica/lasersdk/dlcpro/v1_6_1.py
toptica/lasersdk/dlcpro/v1_6_3.py
toptica/lasersdk/dlcpro/v1_7_0.py
toptica/lasersdk/dlcpro/v1_8_1.py
toptica/lasersdk/dlcpro/v1_9_0.py
toptica/lasersdk/dlcpro/v2_0_1.py
toptica_lasersdk-3.2.0.dist-info/LICENSE.txt
toptica_lasersdk-3.2.0.dist-info/METADATA
toptica_lasersdk-3.2.0.dist-info/WHEEL
toptica_lasersdk-3.2.0.dist-info/entry_points.txt
toptica_lasersdk-3.2.0.dist-info/namespace_packages.txt
toptica_lasersdk-3.2.0.dist-info/top_level.txt
toptica_lasersdk-3.2.0.dist-info/RECORD
