Metadata-Version: 2.1
Name: toptica-lasersdk
Version: 3.2.0
Summary: TOPTICA Python Laser SDK
Home-page: https://toptica.github.io/python-lasersdk/
Author: TOPTICA Photonics AG
Author-email: info@toptica.com
License: MIT
Keywords: toptica photonics laser sdk dlcpro ichrome cle mle
Classifier: Development Status :: 5 - Production/Stable
Classifier: Intended Audience :: Developers
Classifier: Topic :: Software Development :: Libraries
Classifier: Topic :: Software Development :: Libraries :: Python Modules
Classifier: License :: OSI Approved :: MIT License
Classifier: Programming Language :: Python :: 3
Classifier: Programming Language :: Python :: 3.6
Classifier: Programming Language :: Python :: 3.7
Classifier: Programming Language :: Python :: 3.8
Classifier: Programming Language :: Python :: 3.9
Classifier: Programming Language :: Python :: 3.10
Classifier: Programming Language :: Python :: 3.11
Classifier: Programming Language :: Python :: 3.12
Requires-Python: >=3.6,<4
License-File: LICENSE.txt
Requires-Dist: ifaddr
Requires-Dist: pyserial
